lonelypss/__main__.py
lonelypss/main.py
lonelypss/py.typed
lonelypss/router.py
lonelypss/bknd/sweep_missed.py
lonelypss/config/config.py
lonelypss/config/lifespan.py
lonelypss/config/set_subscriptions_info.py
lonelypss/config/helpers/sqlite_db_config.py
lonelypss/middleware/config.py
lonelypss/middleware/ws_receiver.py
lonelypss/routes/check_subscriptions.py
lonelypss/routes/missed_for_websockets.py
lonelypss/routes/notify.py
lonelypss/routes/receive_for_websockets.py
lonelypss/routes/set_subscriptions.py
lonelypss/routes/subscribe_exact.py
lonelypss/routes/subscribe_glob.py
lonelypss/routes/unsubscribe_exact.py
lonelypss/routes/unsubscribe_glob.py
lonelypss/routes/websocket_endpoint.py
lonelypss/util/async_io.py
lonelypss/util/close_guarded_io.py
lonelypss/util/request_body_io.py
lonelypss/util/sync_io.py
lonelypss/util/websocket_message.py
lonelypss/util/ws_receiver.py
lonelypss/ws/simple_receiver.py
lonelypss/ws/state.py
lonelypss/ws/util.py
lonelypss/ws/handlers/accepting.py
lonelypss/ws/handlers/closing.py
lonelypss/ws/handlers/handler.py
lonelypss/ws/handlers/protocol.py
lonelypss/ws/handlers/waiting_configure.py
lonelypss/ws/handlers/open/check_background_tasks.py
lonelypss/ws/handlers/open/check_compressors.py
lonelypss/ws/handlers/open/check_my_receiver_queue.py
lonelypss/ws/handlers/open/check_process_task.py
lonelypss/ws/handlers/open/check_read_task.py
lonelypss/ws/handlers/open/check_result.py
lonelypss/ws/handlers/open/check_send_task.py
lonelypss/ws/handlers/open/collector_utils.py
lonelypss/ws/handlers/open/compressor_utils.py
lonelypss/ws/handlers/open/errors.py
lonelypss/ws/handlers/open/handler.py
lonelypss/ws/handlers/open/send_receive_stream.py
lonelypss/ws/handlers/open/send_simple_asap.py
lonelypss/ws/handlers/open/websocket_url.py
lonelypss/ws/handlers/open/processors/process_confirm_receive.py
lonelypss/ws/handlers/open/processors/process_continue_receive.py
lonelypss/ws/handlers/open/processors/process_notify.py
lonelypss-0.0.11.dist-info/LICENSE.md
lonelypss-0.0.11.dist-info/METADATA
lonelypss-0.0.11.dist-info/WHEEL
lonelypss-0.0.11.dist-info/entry_points.txt
lonelypss-0.0.11.dist-info/top_level.txt
lonelypss-0.0.11.dist-info/RECORD
