Metadata-Version: 2.2
Name: lonelypss
Version: 0.0.11
Summary: PubSub over HTTP
Author-email: Timothy Moore <mtimothy984@gmail.com>
Classifier: Development Status :: 2 - Pre-Alpha
Classifier: Environment :: Web Environment
Classifier: Intended Audience :: Developers
Classifier: License :: OSI Approved :: MIT License
Classifier: Operating System :: OS Independent
Classifier: Programming Language :: Python :: 3
Classifier: Programming Language :: Python :: 3.9
Classifier: Programming Language :: Python :: 3.10
Classifier: Programming Language :: Python :: 3.11
Classifier: Programming Language :: Python :: 3.12
Classifier: Programming Language :: Python :: 3.13
Requires-Python: >=3.9
License-File: LICENSE.md
Requires-Dist: fastapi>=0.115
Requires-Dist: aiohttp>=3.11
Requires-Dist: lonelypsp>=0.0.40
Provides-Extra: standard
Requires-Dist: uvicorn>=0.32; extra == "standard"
Requires-Dist: colorama>=0.4; sys_platform == "win32" and extra == "standard"
Requires-Dist: httptools>=0.6.3; extra == "standard"
Requires-Dist: python-dotenv>=0.13; extra == "standard"
Requires-Dist: PyYAML>=5.1; extra == "standard"
Requires-Dist: uvloop!=0.15.0,!=0.15.1,>=0.14.0; (sys_platform != "win32" and (sys_platform != "cygwin" and platform_python_implementation != "PyPy")) and extra == "standard"
Requires-Dist: watchfiles>=0.13; extra == "standard"
Requires-Dist: websockets>=10.4; extra == "standard"
Requires-Dist: zstandard>=0.23; extra == "standard"
